<?xml version="1.0" encoding="UTF-8"?>
<tei xml:space="preserve" xmlns="http://www.tei-c.org/ns/1.0" xmlns:xlink="http://www.w3.org/1999/xlink" xmlns:mml="http://www.w3.org/1998/Math/MathML">
	<teiHeader>
		<fileDesc>
			<sourceDesc>
				<biblStruct>
					<analytic>

						<author>
							<persName>
								 <forename>Kenshi</forename>
								 <surname>Matsuno</surname>
								 <marker>1</marker>
							</persName>
							<persName>
								 <forename>Hideaki</forename>
								 <surname>Miyamoto</surname>
								 <marker>1</marker>
							</persName>
							<persName>
								 <forename>Hideki</forename>
								 <surname>Kitada</surname>
								 <marker>2</marker>
							</persName>
							<persName>
								 <forename>Shinichi</forename>
								 <surname>Yoshimatsu</surname>
								 <marker>3</marker>
							</persName>
							<persName>
								 <forename>Fumio</forename>
								 <surname>Tamura</surname>
								 <marker>4</marker>
							</persName>
							<persName>
								 <forename>Kouichi</forename>
								 <surname>Sakurai</surname>
								 <marker>5</marker>
							</persName>
							<persName>
								 <forename>Kotaro</forename>
								 <surname>Fukubayashi</surname>
								 <marker>6</marker>
							</persName>
							<persName>
								 <forename>Takashi</forename>
								 <surname>Shono</surname>
								 <marker>7</marker>
							</persName>
							<persName>
								 <forename>Hiroko</forename>
								 <surname>Setoyama</surname>
								 <marker>1,8</marker>
							</persName>
							<persName>
								 <forename>Taichi</forename>
								 <surname>Matsuyama</surname>
								 <marker>9</marker>
							</persName>
							<persName>
								 <forename>Shinichiro</forename>
								 <surname>Suko</surname>
								 <marker>10</marker>
							</persName>
							<persName>
								 <forename>Rei</forename>
								 <surname>Narita</surname>
								 <marker>11</marker>
							</persName>
							<persName>
								 <forename>Munenori</forename>
								 <surname>Honda</surname>
								 <marker>1</marker>
							</persName>
							<persName>
								 <forename>Masakuni</forename>
								 <surname>Tateyama</surname>
								 <marker>1</marker>
							</persName>
							<persName>
								 <forename>Hideaki</forename>
								 <surname>Naoe</surname>
								 <marker>1</marker>
							</persName>
							<persName>
								 <forename>Jun</forename>
								 <surname>Morinaga</surname>
								 <marker>12</marker>
							</persName>
							<persName>
								 <forename>Yasuhito</forename>
								 <surname>Tanaka</surname>
								 <marker>1</marker>
							</persName>
							<persName>
								 <forename>Ryosuke</forename>
								 <surname>Gushima</surname>
								 <marker>1</marker>
							</persName>
							<persName>
								 <forename>Yasuhito</forename>
								 <surname>Tanaka</surname>,
							</persName>
						</author>

					</analytic>
				</biblStruct>
			</sourceDesc>
		</fileDesc>
	</teiHeader>
</tei>
