<tei>
    <teiHeader>
        <fileDesc xml:id="_Retzler 2018.pdf"/>
    </teiHeader>
    <text xml:lang="en">


		<figure type="table">

            <head>Table </head>
 
            <label>1 </label>
 
            <figDesc>Health states<lb/> a Assumes that during the pollen season, comorbid perennial allergy symptoms are combined with ARC symptoms and do not require additional<lb/> health states<lb/> b Assumes that utility would be normal in patients with seasonal ARC and no comorbidities regardless of severity<lb/> </figDesc>
<lb/> 
            <table>During the Pollen season<lb/> Health state for elicitation<lb/> Diagnosis<lb/> ARC severity<lb/> (seasonal aller-<lb/>gies)<lb/> Severity of comorbid asthma Presence of comor-<lb/>bid perennial allergic<lb/> rhinitis?<lb/> 1 Seasonal ARC<lb/> Mild<lb/> -<lb/>n/a a<lb/> Mild ARC<lb/> 2 Seasonal ARC<lb/> Moderate<lb/> -<lb/>n/a a<lb/> Moderate ARC<lb/> 3 Seasonal ARC<lb/> Severe<lb/> -<lb/>n/a a<lb/> Severe ARC<lb/> 4 Seasonal ARC with asthma<lb/> Mild<lb/> Well-to-partly controlled<lb/> n/a a<lb/> Mild ARC + well-to-partly<lb/> controlled asthma<lb/> 5 Seasonal ARC with asthma<lb/> Mild<lb/> Uncontrolled<lb/> n/a a<lb/> Mild ARC + uncontrolled<lb/> asthma<lb/> 6 Seasonal ARC with asthma<lb/> Moderate<lb/> Well-to-partly controlled<lb/> n/a a<lb/> Moderate ARC + well-to-partly<lb/> controlled asthma<lb/> 7 Seasonal ARC with asthma<lb/> Moderate<lb/> Uncontrolled<lb/> n/a a<lb/> Moderate ARC + uncontrolled<lb/> asthma<lb/> 8 Seasonal ARC with asthma<lb/> Severe<lb/> Well-to-partly controlled<lb/> n/a a<lb/> Severe ARC + well-to-partly<lb/> controlled asthma<lb/> 9 Seasonal ARC with asthma<lb/> Severe<lb/> Uncontrolled<lb/> n/a a<lb/> Severe ARC + uncontrolled<lb/> asthma<lb/> Outside the Pollen season<lb/> Health state for elicitation<lb/> Diagnosis<lb/> ARC severity<lb/> (seasonal aller-<lb/>gies)b<lb/> Severity of comorbid asthma Presence of comor-<lb/>bid perennial allergic<lb/> rhinitis?<lb/> 10 Seasonal ARC and perennial<lb/> AR<lb/> -<lb/>-<lb/>Yes<lb/> Perennial AR<lb/> 11 Seasonal ARC with asthma<lb/> -<lb/>Well-to-partly controlled<lb/> -<lb/>Well-to-partly controlled<lb/> asthma<lb/> 12 Seasonal ARC with asthma<lb/> -<lb/>Uncontrolled<lb/> -<lb/>Uncontrolled asthma<lb/> 13 Seasonal ARC and perennial<lb/> AR with asthma<lb/> -<lb/>Well-to-partly controlled<lb/> Yes<lb/> Perennial AR + well-to-<lb/>partly controlled asthma<lb/> 14 Seasonal ARC and perennial<lb/> AR with asthma<lb/> -<lb/>Uncontrolled<lb/> Yes<lb/> Perennial AR + uncon-<lb/>trolled asthma</table>
		</figure>


		<figure type="table">

            <head>Table </head>
 
            <label>2 </label>
 
            <figDesc>Sample characteristics<lb/> a Targets represent averaged country-specific demographic weight-<lb/>ings derived from Eurostat 2015 data. Full country-by-country break-<lb/>downs are available in Supplementary Material SA. These were used<lb/> for quota implementation during recruitment<lb/> </figDesc>
<lb/> 
            <table>Demographic<lb/> Adult<lb/> Child<lb/> Target a<lb/> (Where<lb/> applica-<lb/>ble)<lb/> Age group<lb/> 8-11<lb/> -<lb/>1082 (100%)<lb/> -<lb/>18-24<lb/> 156 (10.7%)<lb/> -<lb/>10.5%<lb/> 25-34<lb/> 248 (17.1%)<lb/> -<lb/>16.8%<lb/> 35-44<lb/> 250 (17.2%)<lb/> -<lb/>17.0%<lb/> 45-54<lb/> 260 (17.9%)<lb/> -<lb/>17.8%<lb/> 55-64<lb/> 232 (16.0%)<lb/> -<lb/>15.8%<lb/> 65 and over<lb/> 308 (21.2%)<lb/> -<lb/>22.3%<lb/> Gender<lb/> Male<lb/> 708 (48.7%)<lb/> 523 (48.3%)<lb/> 48.7%<lb/> Female<lb/> 746 (51.3%)<lb/> 559 (51.7%)<lb/> 51.3%<lb/> Self-reported relevant diagnoses<lb/> ARC<lb/> 500 (34.4%)<lb/> 596 (55.1%)<lb/> -<lb/>AR<lb/> 327(22.5%)<lb/> 422 (39.0%)<lb/> -<lb/>Asthma<lb/> 259 (17.8%)<lb/> 257 (23.8%)<lb/> -<lb/>Utilities<lb/> Examination of box-and-whisker plots indicated that adult<lb/> utilities lower than 0.3 were statistical outliers (&gt; 1.5 inter-<lb/>quartile ranges below the lower quartile). These values were<lb/> also considered to be lacking face validity, and indicative of<lb/> respondents not responding in a thoughtful manner or having<lb/> misunderstood the question. The child data included greater<lb/> numbers of low utility values, and those lower than 0.3 were<lb/> not outliers according to the interquartile range (IQR) rule<lb/> (greater than 1.5 × IQR above the upper or below the lower<lb/> quartile); however, values below this level were still consid-<lb/>ered to be lacking face validity and thus, for both datasets,<lb/> responses for individuals who produced ratings lower than<lb/> 0.3 for any health state were removed. This resulted in inclu-<lb/>sion of 1235 adults (exclusions per country: UK: 54; France:<lb/> 55; Germany: 53; Slovakia: 57) and 423 children (exclu-<lb/>sions per country: UK: 133; France: 151; Germany: 166;<lb/> Slovakia: 209). The impact of different exclusion criteria on<lb/> sample size and utility estimates was examined in sensitivity<lb/> analyses (see Supplementary Material B). Average utilities<lb/> obtained are shown in Table</table>
		</figure>


		<figure type="table">

            <head>Table </head>
 
            <label>3 </label>
 
            <figDesc>Average adult and child utilities<lb/> SE standard error of the mean, IQR interquartile range<lb/> </figDesc>
<lb/> 
            <table>No. Health state<lb/> Utilities<lb/> Adult<lb/> Child<lb/> N<lb/> Mean (SE)<lb/> Median (IQR)<lb/> N<lb/> Mean (SE)<lb/> Median (IQR)<lb/> 1<lb/> Well-to-partly controlled asthma<lb/> 709 0.874 (0.006) 0.949 (0.800-0.993) 232 0.693 (0.011) 0.700 (0.560-0.820)<lb/> 2<lb/> Uncontrolled asthma<lb/> 710 0.829 (0.006) 0.884 (0.737-0.952) 227 0.635 (0.012) 0.620 (0.500-0.770)<lb/> 3<lb/> Mild ARC<lb/> 714 0.880 (0.006) 0.967 (0.804-0.996) 252 0.705 (0.011) 0.700 (0.590-0.850)<lb/> 4<lb/> Mild ARC + well-to-partly controlled asthma<lb/> 700 0.872 (0.006) 0.947 (0.800-0.993) 253 0.677 (0.010) 0.690 (0.540-0.790)<lb/> 5<lb/> Mild ARC + uncontrolled asthma<lb/> 714 0.844 (0.006) 0.900 (0.754-0.980) 250 0.643 (0.010) 0.640 (0.510-0.753)<lb/> 6<lb/> Moderate ARC<lb/> 709 0.864 (0.006) 0.901 (0.799-0.986) 249 0.675 (0.010) 0.680 (0.550-0.800)<lb/> 7<lb/> Moderate ARC + well-to-partly controlled asthma 688 0.847 (0.006) 0.900 (0.775-0.981) 252 0.668 (0.010) 0.660 (0.560-0.780)<lb/> 8<lb/> Moderate ARC + uncontrolled asthma<lb/> 711 0.828 (0.006) 0.886 (0.745-0.962) 240 0.647 (0.011) 0.635 (0.510-0.788)<lb/> 9<lb/> Severe ARC<lb/> 707 0.831 (0.006) 0.888 (0.733-0.973) 223 0.666 (0.011) 0.660 (0.550-0.780)<lb/> 10 Severe ARC + well-to-partly controlled asthma<lb/> 718 0.845 (0.006) 0.900 (0.774-0.981) 243 0.663 (0.010) 0.660 (0.520-0.790)<lb/> 11 Severe ARC + uncontrolled asthma<lb/> 712 0.812 (0.006) 0.851 (0.708-0.948) 223 0.635 (0.011) 0.610 (0.500-0.760)<lb/> 12 Perennial AR<lb/> 697 0.842 (0.006) 0.899 (0.763-0.977) 247 0.655 (0.010) 0.650 (0.520-0.770)<lb/> 13 Perennial AR + well-to-partly controlled asthma<lb/> 694 0.849 (0.006) 0.900 (0.790-0.979) 248 0.650 (0.010) 0.650 (0.520-0.750)<lb/> 14 Perennial AR + uncontrolled asthma<lb/> 697 0.818 (0.006) 0.852 (0.709-0.960) 245 0.638 (0.012) 0.630 (0.500-0.790)</table>
		</figure>


		<figure type="table">

            <head>Table </head>
 
            <label>4 </label>
 
            <figDesc>Average adult and child disutilities<lb/> SEM standard error of the mean, IQR interquartile range<lb/> </figDesc>
<lb/> 
            <table>Adult<lb/> Child<lb/> N<lb/> Mean (SE)<lb/> Median (IQR)<lb/> N<lb/> Mean (SE)<lb/> Median (IQR)<lb/> Impact of increased severity<lb/> Mild ARC<lb/> Moderate ARC<lb/> 277<lb/> 0.054 (0.005)<lb/> 0.019 (0.002-0.081)<lb/> 93<lb/> 0.131 (0.013)<lb/> 0.100 (0.030-0.205)<lb/> Severe ARC<lb/> 283<lb/> 0.085 (0.006)<lb/> 0.047 (0.007-0.117)<lb/> 69<lb/> 0.121 (0.015)<lb/> 0.090 (0.020-0.175)<lb/> Moderate ARC<lb/> Severe ARC<lb/> 251<lb/> 0.065 (0.005)<lb/> 0.030 (0.003-0.098)<lb/> 74<lb/> 0.101 (0.013)<lb/> 0.065 (0.010-0.153)<lb/> Well-to-partly controlled asthma<lb/> Uncontrolled asthma<lb/> 293<lb/> 0.091 (0.006)<lb/> 0.057 (0.011-0.118)<lb/> 67<lb/> 0.155 (0.020)<lb/> 0.090 (0.030-0.240)<lb/> Impact of comorbidity<lb/> Mild ARC<lb/> + Well-to-partly controlled asthma<lb/> 231<lb/> 0.048 (0.006)<lb/> 0.011 (0.001-0.058)<lb/> 93<lb/> 0.089 (0.008)<lb/> 0.070 (0.025-0.140)<lb/> + Uncontrolled asthma<lb/> 272<lb/> 0.070 (0.005)<lb/> 0.040 (0.005-0.101)<lb/> 87<lb/> 0.172 (0.017)<lb/> 0.130 (0.030-0.290)<lb/> Moderate ARC<lb/> + Well-to-partly controlled asthma<lb/> 216<lb/> 0.058 (0.006)<lb/> 0.017 (0.000-0.087)<lb/> 81<lb/> 0.098 (0.011)<lb/> 0.070 (0.020-0.130)<lb/> + Uncontrolled asthma<lb/> 291<lb/> 0.067 (0.005)<lb/> 0.033 (0.004-0.101)<lb/> 86<lb/> 0.116 (0.012)<lb/> 0.090 (0.020-0.180)<lb/> Severe ARC<lb/> + Well-to-partly controlled asthma<lb/> 229<lb/> 0.053 (0.006)<lb/> 0.013 (0.003-0.071)<lb/> 69<lb/> 0.094 (0.013)<lb/> 0.070 (0.010-0.125)<lb/> + Uncontrolled asthma<lb/> 245<lb/> 0.065 (0.005)<lb/> 0.037 (0.004-0.100)<lb/> 74<lb/> 0.104 (0.011)<lb/> 0.090 (0.020-0.153)<lb/> 1 3</table>
		</figure>



    </text>
</tei>

