<tei>
    <teiHeader>
        <fileDesc xml:id="_Tsuji 2023.pdf"/>
    </teiHeader>
    <text xml:lang="en">


        <figure>

            <figDesc>J o u r n a l P r e -p r o o f</figDesc>
        </figure>


        <figure>

            <head>N=192<lb/> <head>J </head>
 
            <figDesc>o u r n a l P r e -p r o o f<lb/> This conceptual diagram was originally schematized by the author. Knowledge of ICI irAE is associated<lb/> with personal attributes and environmental characteristics. Awareness of irAE is associated with personal<lb/> attributes, environmental characteristics and knowledge of ICI and irAE. Personal attributes are associated with<lb/> environmental characteristics.</figDesc>
        </figure>


        <figure>

            <head>Figure</head>

            <label>. </label>
 
            <figDesc>Conceptual diagram of ICI and irAE knowledge, attributes, and awareness of irAEs<lb/> J o u r n a l P r e -p r o o f</figDesc>
        </figure>



    </text>
</tei>

